arc_agi_core/__init__.py
arc_agi_core/_dataset.py
arc_agi_core/_errors.py
arc_agi_core/_grid.py
arc_agi_core/_pair.py
arc_agi_core/_symbols.py
arc_agi_core/_task.py
arc_agi_core/_utils.py
arc_agi_core-0.1.14.dist-info/METADATA
arc_agi_core-0.1.14.dist-info/WHEEL
arc_agi_core-0.1.14.dist-info/RECORD
