Metadata-Version: 2.4
Name: arc-agi-core
Version: 0.1.14
Summary: Research tool-kit for tackling ARC(Abstraction and Reasoning Corpus). 
Requires-Python: >=3.10
Requires-Dist: numpy>=2.2.4
Requires-Dist: requests>=2.32.3
Requires-Dist: svg-py>=1.6.0
